expressql/__init__.py
expressql/base.py
expressql/dsl.py
expressql/exceptions.py
expressql/functions.py
expressql/utils.py
expressql/validators.py
expressql/parsers/__init__.py
expressql/parsers/conditions_parser.py
expressql/parsers/expressions_parser.py
expressql/parsers/main.py
expressql/parsers/parsing_utils.py
expressql/parsers/subquery_placeholder.py
expressql-1.0.0.dist-info/licenses/LICENSE
expressql-1.0.0.dist-info/METADATA
expressql-1.0.0.dist-info/WHEEL
expressql-1.0.0.dist-info/top_level.txt
expressql-1.0.0.dist-info/RECORD
