Metadata-Version: 2.4
Name: expressql
Version: 1.0.0
Summary: A Pythonic DSL for SQL conditions and expressions.
Author-email: Grayjou <cgrayjou@gmail.com>
License: MIT License
Project-URL: Homepage, https://github.com/Grayjou/ExpressQL
Project-URL: Repository, https://github.com/Grayjou/ExpressQL
Project-URL: Bug Tracker, https://github.com/Grayjou/ExpressQL/issues
Project-URL: Changelog, https://github.com/Grayjou/ExpressQL/blob/main/expressql/changelog.md
Keywords: SQL,DSL,query builder,query conditions,SQL expressions,ORM,database,Python SQL,chained comparisons,data access,placeholder management,pythonic syntax,logical operators,SQL functions
Classifier: Development Status :: 5 - Production/Stable
Classifier: Intended Audience :: Developers
Classifier: Programming Language :: Python :: 3
Classifier: Programming Language :: Python :: 3.8
Classifier: Programming Language :: Python :: 3.9
Classifier: Programming Language :: Python :: 3.10
Classifier: Programming Language :: Python :: 3.11
Classifier: Programming Language :: Python :: 3.12
Classifier: Programming Language :: Python :: 3.13
Classifier: Programming Language :: Python :: 3.14
Classifier: License :: OSI Approved :: MIT License
Classifier: Operating System :: OS Independent
Classifier: Topic :: Database
Classifier: Topic :: Software Development :: Libraries :: Python Modules
Requires-Python: >=3.8
License-File: LICENSE
Provides-Extra: parsing
Requires-Dist: sqlparse>=0.4.0; extra == "parsing"
Provides-Extra: dev
Requires-Dist: pytest>=7.0.0; extra == "dev"
Requires-Dist: pytest-cov>=4.0.0; extra == "dev"
Requires-Dist: sqlparse>=0.4.0; extra == "dev"
Provides-Extra: docs
Requires-Dist: sphinx>=8.0.0; extra == "docs"
Requires-Dist: sphinx-rtd-theme>=3.0.0; extra == "docs"
Requires-Dist: sphinx-autodoc-typehints>=3.0.0; extra == "docs"
Dynamic: license-file
